{
    "name": "TomatoCube Arcade Sprites",
    "dependencies": {
        "device": "*"
    },
    "description": "Additional sprites made with love",
    "icon": "https://raw.githubusercontent.com/TomatoCube18/tomatocube-arcade-sprites/master/icon.png",
    "files": [
        "main.blocks",
        "main.ts",
        "README.md",
        "sprites.jres",
        "sprites.ts",
        "logo.jres",
        "logo.ts"
    ],
    "preferredEditor": "blocksprj",
    "testFiles": [
        "test.ts"
    ]
}
